emout/__init__.py
emout/distributed/__init__.py
emout/distributed/client.py
emout/distributed/clusters.py
emout/distributed/config.py
emout/distributed/utils.py
emout/emout/__init__.py
emout/emout/extraction.py
emout/emout/facade.py
emout/emout/units.py
emout/emout/backtrace/__init__.py
emout/emout/backtrace/backtrace_result.py
emout/emout/backtrace/multi_backtrace_result.py
emout/emout/backtrace/probability_result.py
emout/emout/backtrace/solver_wrapper.py
emout/emout/backtrace/xy_data.py
emout/emout/data/__init__.py
emout/emout/data/data.py
emout/emout/data/griddata_series.py
emout/emout/data/vector_data.py
emout/emout/io/__init__.py
emout/emout/io/directory.py
emout/emout/io/grid.py
emout/emout/relocation/__init__.py
emout/emout/relocation/electric.py
emout/emout/relocation/magnetic.py
emout/plot/__init__.py
emout/plot/animation_plot.py
emout/plot/basic_plot.py
emout/plot/extra_plot.py
emout/plot/plot_cross_sections.py
emout/utils/__init__.py
emout/utils/eflux.py
emout/utils/emsesinp.py
emout/utils/group.py
emout/utils/poisson.py
emout/utils/units.py
emout/utils/util.py
emout-2.4.4.dist-info/licenses/LICENSE
emout-2.4.4.dist-info/METADATA
emout-2.4.4.dist-info/WHEEL
emout-2.4.4.dist-info/top_level.txt
emout-2.4.4.dist-info/RECORD
