Metadata-Version: 2.4
Name: emout
Version: 2.4.4
Summary: Emses output manager
Author-email: Nkzono99 <j-nakazono@stu.kobe-u.ac.jp>
Maintainer-email: Nkzono99 <j-nakazono@stu.kobe-u.ac.jp>
License-Expression: MIT
Project-URL: Repository, https://github.com/Nkzono99/emout.git
Keywords: Visualization,Simulation,EMSES
Classifier: Operating System :: OS Independent
Classifier: Programming Language :: Python
Classifier: Programming Language :: Python :: 3
Classifier: Programming Language :: Python :: 3 :: Only
Classifier: Programming Language :: Python :: 3.8
Classifier: Programming Language :: Python :: 3.9
Classifier: Programming Language :: Python :: 3.10
Classifier: Programming Language :: Python :: 3.11
Classifier: Programming Language :: Python :: 3.12
Requires-Python: >=3.7
License-File: LICENSE
Requires-Dist: numpy
Requires-Dist: matplotlib
Requires-Dist: h5py
Requires-Dist: f90nml
Requires-Dist: scipy
Requires-Dist: pandas
Requires-Dist: tqdm
Requires-Dist: dask; python_version >= "3.10"
Requires-Dist: distributed; python_version >= "3.10"
Dynamic: license-file
